pysaavn/__init__.py
pysaavn/api.py
pysaavn/cli.py
pysaavn/wrappers.py
pysaavn-2022.dist-info/LICENSE.txt
pysaavn-2022.dist-info/METADATA
pysaavn-2022.dist-info/WHEEL
pysaavn-2022.dist-info/entry_points.txt
pysaavn-2022.dist-info/top_level.txt
pysaavn-2022.dist-info/zip-safe
pysaavn-2022.dist-info/RECORD
