Metadata-Version: 2.1
Name: pysaavn
Version: 2022
Summary: A Minimal Client for JioSaavn
Home-page: https://github.com/RanjodhSingh1729/PySaavn
Author: Ranjodh Singh
Author-email: ranjodhsingh1729@gmail.com
License: MIT License
Keywords: music,songs,jiosaavn
Classifier: License :: OSI Approved :: MIT License
Classifier: Programming Language :: Python :: 3
Classifier: Operating System :: OS Independent
License-File: LICENSE.txt
Requires-Dist: wget
Requires-Dist: pyDes
Requires-Dist: requests
Requires-Dist: InquirerPy
